hexadruid/__init__.py
hexadruid/hexadruid.cp311-win_amd64.pyd
hexadruid/hexadruid.py
hexadruid/hexadruid.pyi
hexadruid-0.2.2.dist-info/licenses/LICENSE
hexadruid-0.2.2.dist-info/METADATA
hexadruid-0.2.2.dist-info/WHEEL
hexadruid-0.2.2.dist-info/entry_points.txt
hexadruid-0.2.2.dist-info/top_level.txt
hexadruid-0.2.2.dist-info/RECORD
