Metadata-Version: 2.4
Name: hexadruid
Version: 0.2.2
Summary: Advanced Spark Data Skew, Schema, and Partitioning Optimizer
Home-page: https://github.com/OmarAttia95/hexadruid
Author: Omar Hossam Attia
Author-email: omar@123915@hotmail.com
Classifier: Programming Language :: Python :: 3
Classifier: License :: OSI Approved :: MIT License
Classifier: Operating System :: OS Independent
Requires-Python: >=3.8
License-File: LICENSE
Requires-Dist: pyspark<4.0.0,>=3.5.0
Requires-Dist: pandas>=1.0
Requires-Dist: matplotlib>=3.0
Requires-Dist: python-dateutil>=2.8
Provides-Extra: dev
Requires-Dist: pytest>=6.0; extra == "dev"
Requires-Dist: flake8; extra == "dev"
Requires-Dist: black; extra == "dev"
Provides-Extra: viz
Requires-Dist: seaborn>=0.11; extra == "viz"
Dynamic: author
Dynamic: author-email
Dynamic: classifier
Dynamic: description
Dynamic: description-content-type
Dynamic: home-page
Dynamic: license-file
Dynamic: provides-extra
Dynamic: requires-dist
Dynamic: requires-python
Dynamic: summary
